openbandparams/__init__.py
openbandparams/algorithms.py
openbandparams/alloy.py
openbandparams/equations.py
openbandparams/iii_v_alloy.py
openbandparams/iii_v_zinc_blende_alloy.py
openbandparams/iii_v_zinc_blende_binaries.py
openbandparams/iii_v_zinc_blende_binary.py
openbandparams/iii_v_zinc_blende_mixed_alloy.py
openbandparams/iii_v_zinc_blende_quaternaries.py
openbandparams/iii_v_zinc_blende_quaternary.py
openbandparams/iii_v_zinc_blende_strained.py
openbandparams/iii_v_zinc_blende_ternaries.py
openbandparams/iii_v_zinc_blende_ternary.py
openbandparams/parameter.py
openbandparams/reference.py
openbandparams/references.py
openbandparams/version.py
openbandparams/examples/Binaries.py
openbandparams/examples/GaPSb_on_InP.py
openbandparams/examples/Parameters.py
openbandparams/examples/Plot_Band_Offset_vs_Composition_of_Ternary.py
openbandparams/examples/Plot_Band_Offset_vs_Lattice_Constant.py
openbandparams/examples/Plot_Band_Offset_vs_Lattice_Constant_No_Phosphides.py
openbandparams/examples/Plot_Band_Offset_vs_Lattice_Constant_of_Strained_Binaries.py
openbandparams/examples/Plot_Bandgap_vs_Composition_of_Quaternary3.py
openbandparams/examples/Plot_Bandgap_vs_Composition_of_Ternary.py
openbandparams/examples/Plot_Bandgap_vs_Lattice_Constant.py
openbandparams/examples/Plot_Bandgap_vs_Lattice_Constant_of_Quaternary1or2.py
openbandparams/examples/Plot_Bandgap_vs_Lattice_Constant_of_Quaternary3.py
openbandparams/examples/Plot_Bandgap_vs_Lattice_Constant_of_Strained_Binaries.py
openbandparams/examples/Plot_Conduction_Band_Offset_vs_Lattice_Constant.py
openbandparams/examples/Plot_InGaAsP_lattice_matched_InP.py
openbandparams/examples/Plot_Valance_Band_Offset_vs_Lattice_Constant.py
openbandparams/examples/Plot_refractive_index_quaternaries_lattice_matched_inp.py
openbandparams/examples/Quaternaries.py
openbandparams/examples/References.py
openbandparams/examples/Strained_Parameters.py
openbandparams/examples/Strained_Ternaries.py
openbandparams/examples/Ternaries.py
openbandparams-1.0.dist-info/licenses/LICENSE.txt
openbandparams-1.0.dist-info/METADATA
openbandparams-1.0.dist-info/WHEEL
openbandparams-1.0.dist-info/top_level.txt
openbandparams-1.0.dist-info/zip-safe
openbandparams-1.0.dist-info/RECORD
