Metadata-Version: 2.4
Name: openbandparams
Version: 1.0
Summary: open source semiconductor band parameters
Author-email: "Scott J. Maddox" <smaddox@utexas.edu>, Duarte Silva <d.j.fernandes.da.silva@tue.nl>
Maintainer-email: Duarte Silva <d.j.fernandes.da.silva@tue.nl>
Project-URL: Homepage, https://github.com/duarte-jfs/openbandparams
Requires-Python: >=3.6
License-File: LICENSE.txt
Requires-Dist: distro
Requires-Dist: numpy
Provides-Extra: test
Requires-Dist: pytest; extra == "test"
Dynamic: license-file
